hahahexample/__init__.py
hahahexample/hahahexample.py
hahahexample-0.0.1.dist-info/LICENSE
hahahexample-0.0.1.dist-info/METADATA
hahahexample-0.0.1.dist-info/WHEEL
hahahexample-0.0.1.dist-info/top_level.txt
hahahexample-0.0.1.dist-info/RECORD
